quick_manage/__init__.py
quick_manage/_common.py
quick_manage/certs.py
quick_manage/config.py
quick_manage/environment.py
quick_manage/files.py
quick_manage/hosts.py
quick_manage/cli/__init__.py
quick_manage/cli/certificates.py
quick_manage/cli/common.py
quick_manage/cli/context.py
quick_manage/cli/hosts.py
quick_manage/cli/keys.py
quick_manage/cli/main.py
quick_manage/cli/ssh.py
quick_manage/context/__init__.py
quick_manage/context/_common.py
quick_manage/file/__init__.py
quick_manage/file/_common.py
quick_manage/file/file_system.py
quick_manage/file/folder_key_store.py
quick_manage/file/local_file_context.py
quick_manage/impl_helpers/__init__.py
quick_manage/impl_helpers/key_store_helpers.py
quick_manage/impl_helpers/serialization.py
quick_manage/keys/__init__.py
quick_manage/keys/_common.py
quick_manage/keys/_letsencrypt.py
quick_manage/s3/__init__.py
quick_manage/s3/config.py
quick_manage/s3/s3_store.py
quick_manage/ssh/__init__.py
quick_manage/ssh/client.py
quick_manage/ssh/docker.py
quick_manage/ssh/keys.py
quick_manage/ssh/users.py
quick_manage-0.1.0.dist-info/LICENSE
quick_manage-0.1.0.dist-info/METADATA
quick_manage-0.1.0.dist-info/WHEEL
quick_manage-0.1.0.dist-info/entry_points.txt
quick_manage-0.1.0.dist-info/top_level.txt
quick_manage-0.1.0.dist-info/RECORD
