Metadata-Version: 2.1
Name: quick-manage
Version: 0.1.0
Summary: Quick and lightweight management tools for small IT infrastructure
Home-page: https://github.com/mattj23/quick-manage
Author: Matthew Jarvis
Author-email: mattj23@gmail.com
Classifier: Programming Language :: Python :: 3
Classifier: License :: OSI Approved :: MIT License
Classifier: Operating System :: OS Independent
Requires-Python: >=3.8
License-File: LICENSE
Requires-Dist: cryptography (~=38.0.4)
Requires-Dist: urllib3 (~=1.26.13)
Requires-Dist: paramiko (~=2.12.0)
Requires-Dist: invoke (~=1.7.3)
Requires-Dist: setuptools (~=60.2.0)
Requires-Dist: fabric (~=2.7.1)
Requires-Dist: minio (~=7.1.12)
Requires-Dist: click (~=8.1.3)
Requires-Dist: pytest (~=7.2.0)
Requires-Dist: dacite (~=1.6.0)
Requires-Dist: ruamel.yaml (~=0.17.21)
